FPGA/verilog_working_directory/src/FPGA_prototyping_by_verilog_basics/04_memory.v
module d_flip_flop(
	input wire clk,
	input wire d,
	output reg q
	);

	always @(posedge(clk))
		q = d;
endmodule

module d_flip_flop_with_async_reset(
	input wire clk,
	input wire d,
 	input wire reset,
	output reg q
	);

	always @(posedge(clk), posedge(reset)) begin
		if (reset) 
			q = 1'b0;
		else
			q = d;
	end
endmodule

module d_flip_flop_with_async_reset_sync_enable(
	input wire clk,
	input wire d,
	input wire reset,
	input wire enable,
	output reg q
	);

	always @(posedge(clk), posedge(reset)) begin
		if(reset) 	
			q = 1'b0;
		else if(enable) 
			q = d;
	end
endmodule

module register(
	input wire clk,reset,
	input wire [7:0] d,
	output reg [7:0] q 	
	);

	always @(posedge(clk)) begin
		if(reset) 
			q = 8'b0;
		else 
			q = d;
	end
endmodule

module stimulus();
	// reg d = 1'b0;
	// wire q;
	reg [7:0] d = 0;
	wire [7:0] q;
	reg clk = 1'b0;
	reg reset = 1'b0;
	reg enable = 1'b1;	
	// d_flip_flop_with_async_reset_sync_enable f1(.clk(clk),.d(d),.q(q),.reset(reset),.enable(enable));
	register r(.clk(clk),.reset(reset),.d(d),.q(q)); 
	initial begin
		$dumpfile("simulation.vcd");
		$dumpvars(1,clk,d,q,reset);	
	end

	always 
		#1 clk = ~clk;

	always
		#5 d = d + 1;

	always begin	
		#3 reset = ~ reset;
		#1 reset = ~ reset;
	end

	initial 
		#20 $finish;
endmodule

FPGA/verilog_working_directory/src/FPGA_prototyping_by_verilog_basics/simulation.vcd
$date
	Fri Feb 19 13:27:02 2016
$end
$version
	Icarus Verilog
$end
$timescale
	1s
$end
$scope module stimulus $end
$var reg 1 ! clk $end
$upscope $end
$scope module stimulus $end
$var reg 8 " d [7:0] $end
$upscope $end
$scope module stimulus $end
$var wire 8 # q [7:0] $end
$upscope $end
$scope module stimulus $end
$var reg 1 $ reset $end
$upscope $end
$enddefinitions $end
#0
$dumpvars
0$
bx #
b0 "
0!
$end
#1
b0 #
1!
#2
0!
#3
1!
1$
#4
0!
0$
#5
b1 #
1!
b1 "
#6
0!
#7
b0 #
1!
1$
#8
0!
0$
#9
b1 #
1!
#10
0!
b10 "
#11
b0 #
1!
1$
#12
0!
0$
#13
b10 #
1!
#14
0!
#15
b0 #
1!
1$
b11 "
#16
0!
0$
#17
b11 #
1!
#18
0!
#19
b0 #
1!
1$
#20
0!
0$
b100 "
