FPGA/final_working_projects/seven_segment_display_controller/utils/seven_segment_display.v
/* 
single seven segment led display controller
*/
module seven_segment_display (
	input wire [3:0] digit_to_be_displayed,		// 8 bit binary value of digit to be displayed 0 - 9
	input wire dp,								// decimal point
	output reg [7:0] led 						// output wires to the seven segment display
	);

	always @* begin	
		case(digit_to_be_displayed) 
			4'h0 : led[7:1] = 7'b0000001;
			4'h1 : led[7:1] = 7'b1001111;
			4'h2 : led[7:1] = 7'b0010010;
			4'h3 : led[7:1] = 7'b0000110;
			4'h4 : led[7:1] = 7'b1001100;
			4'h5 : led[7:1] = 7'b0100100;
			4'h6 : led[7:1] = 7'b0100000;
			4'h7 : led[7:1] = 7'b0001111;
			4'h8 : led[7:1] = 7'b0000000;
			4'h9 : led[7:1] = 7'b0000100;
			default : led[7:1] = 7'b1111111;
		endcase
		led[0] = dp;
	end
endmodule

// module test_bench();
// 		reg [3:0] DIGIT_TO_BE_DISPLAYED;
// 		reg DP;
// 		wire [7:0] LED;

// 		seven_segment_display s(.digit_to_be_displayed(DIGIT_TO_BE_DISPLAYED),.dp(DP),.led(LED));	

// 		initial begin
// 			$dumpfile("simulation.vcd");
// 			$dumpvars(0,DIGIT_TO_BE_DISPLAYED,DP,LED);
// 		end

// 		initial begin
// 			DIGIT_TO_BE_DISPLAYED = 0;
// 			DP = 1'b0;
// 		end

// 		always begin
// 			#1 DIGIT_TO_BE_DISPLAYED = DIGIT_TO_BE_DISPLAYED + 1;
// 			if(DIGIT_TO_BE_DISPLAYED == 10) begin
// 					DP = ~ DP;
// 					DIGIT_TO_BE_DISPLAYED = 0;
// 			end
// 		end

// 		initial 
// 			#100 $finish;

// endmodule

FPGA/final_working_projects/ring_shift_register/ring_shift_register.v
/*
parallel output ring shift register
*/
module ring_shift_register #(
		parameter N = 3,
		parameter INITIAL_VALUE = 1
	)(
		input wire clk,
		input wire reset,
		output wire [N-1:0] parallel_out
	);


	// -------- next state logic ------------
	wire [N-1:0] data_next;
	assign data_next = {data[0],data[N-1:1]};
	// ---------------------------------------

	// ----------- register - memory ---------
	reg [N-1:0] data = INITIAL_VALUE;
	always @(posedge(clk),posedge(reset)) begin
		if(reset) begin
			data = INITIAL_VALUE;
		end else begin
			data = data_next;
		end
	end
	//----------------------------------------

	// ---------- output logic ---------------
	assign parallel_out = data;
	// ---------------------------------------

endmodule

// module test_bench();
	
// 	wire [2:0] PARALLEL_OUT;
// 	reg CLK;
//  reg RESET.

// 	localparam N = 3;

// 	ring_shift_register #(.N(N),.INITIAL_VALUE(1)) 
// 	sr1(
// 		.clk(CLK),
// 		.parallel_out(PARALLEL_OUT),
// 		.reset(RESET)
// 	); 

// 	initial begin
// 		$dumpfile("simulation.vcd");
// 		$dumpvars(0,CLK,PARALLEL_OUT,RESET);
// 	end

// 	initial begin
// 		CLK = 1'b0;
//		RESET = 1'b0;
// 	end

// 	always 
// 		#1 CLK = ~ CLK;

// 	initial 
// 		#20 $finish;
// endmodule

FPGA/rana_fpga_working_dirctory/uart_transmitter_core/tick_generator.v
module tick_generator #(
	parameter tick_time = 32'd1000,
	parameter frequency = 32'd100000
	)(
	input wire clk,
	output reg tick);

	reg [32:0] count;
	reg [32:0] count_threshold = tick_time * frequency / 2;
	
	initial begin
		tick = 1'b0;
		count = 32'b0;
	end

	always @(posedge(clk)) begin
		count = count + 1;
		if(count == count_threshold) begin
			count = 0;
			tick = ~ tick;
		end
	end

endmodule

FPGA/verilog_working_directory/src/FPGA_prototyping_by_verilog_basics/seven_segment_display_controller/seven_segment_display_controller.v
`include "tick_generator.v"
`include "ring_shift_register.v"
`include "seven_segment_display.v"

module seven_segment_display_controller(
	input wire CLK,
	output wire [7:0] DISPLAY_BITS,
	output wire LED1,
	output wire LED2,
	output wire LED3,
	output wire LED_CHANGE_TICK,
	output wire VALUE_CHANGE_TICK
	);
	
	// ---------- tick generator --------------
	tick_generator #(.tick_time(32'd1000),.frequency(32'd100000)) 
		led_change_tick(
			.clk(CLK),
			.tick(LED_CHANGE_TICK)
		);
	
	// -------- ring shift register ----------
	ring_shift_register #(.N(3),.INITIAL_VALUE(1)) 
		sr1(
			.clk(LED_CHANGE_TICK),
			.parallel_out({LED1,LED2,LED3})
		);

	// ------- seven segment display ---------
	reg [3:0] led_value_register [2:0];
	
	initial begin
		led_value_register[0] = 1;
		led_value_register[1] = 2;
		led_value_register[2] = 3;
	end

	wire [3:0] led_value;
	reg [2:0] led_value_register_index = 0;
	assign led_value = led_value_register[led_value_register_index];

	seven_segment_display 
		s(
			.digit_to_be_displayed(led_value),
			.dp(1'b0),
			.led(DISPLAY_BITS)
		);

	always @(posedge(LED_CHANGE_TICK)) begin
		led_value_register_index = led_value_register_index + 1;
		if(led_value_register_index == 3) begin 
			led_value_register_index = 0;
		end
	end

endmodule

module stimulus();
	reg clk;
	wire [2:0] led_register;
	wire led_change_tick,value_change_tick;
	wire [7:0] display_bits;

	seven_segment_display_controller
		s(
			.CLK(clk),
			.DISPLAY_BITS(display_bits),
			.LED1(led_register[0]),
			.LED2(led_register[1]),
			.LED3(led_register[2]),
			.LED_CHANGE_TICK(led_change_tick),
			.VALUE_CHANGE_TICK(value_change_tick)
		);

	initial begin
		$dumpfile("simulation.vcd");
		$dumpvars(0,clk,led_register,led_change_tick,value_change_tick,display_bits);
	end

	initial
		clk = 1'b0;

	always 
		#1 clk = ~ clk;

	initial 
		#100 $finish;

endmodule

FPGA/verilog_working_directory/src/FPGA_prototyping_by_verilog_basics/seven_segment_display_controller/simulation.vcd
$date
	Fri Feb 19 19:44:14 2016
$end
$version
	Icarus Verilog
$end
$timescale
	1s
$end
$scope module stimulus $end
$var reg 1 ! clk $end
$upscope $end
$scope module stimulus $end
$var wire 3 " led_register [2:0] $end
$upscope $end
$scope module stimulus $end
$var wire 1 # led_change_tick $end
$upscope $end
$scope module stimulus $end
$var wire 1 $ value_change_tick $end
$upscope $end
$scope module stimulus $end
$var wire 8 % display_bits [7:0] $end
$upscope $end
$enddefinitions $end
#0
$dumpvars
b10011110 %
z$
0#
b100 "
0!
$end
#1
1!
#2
0!
#3
1!
#4
0!
#5
1!
#6
0!
#7
1!
#8
0!
#9
b1 "
b100100 %
1#
1!
#10
0!
#11
1!
#12
0!
#13
1!
#14
0!
#15
1!
#16
0!
#17
1!
#18
0!
#19
0#
1!
#20
0!
#21
1!
#22
0!
#23
1!
#24
0!
#25
1!
#26
0!
#27
1!
#28
0!
#29
b1100 %
b10 "
1#
1!
#30
0!
#31
1!
#32
0!
#33
1!
#34
0!
#35
1!
#36
0!
#37
1!
#38
0!
#39
0#
1!
#40
0!
#41
1!
#42
0!
#43
1!
#44
0!
#45
1!
#46
0!
#47
1!
#48
0!
#49
b100 "
b10011110 %
1#
1!
#50
0!
#51
1!
#52
0!
#53
1!
#54
0!
#55
1!
#56
0!
#57
1!
#58
0!
#59
0#
1!
#60
0!
#61
1!
#62
0!
#63
1!
#64
0!
#65
1!
#66
0!
#67
1!
#68
0!
#69
b100100 %
b1 "
1#
1!
#70
0!
#71
1!
#72
0!
#73
1!
#74
0!
#75
1!
#76
0!
#77
1!
#78
0!
#79
0#
1!
#80
0!
#81
1!
#82
0!
#83
1!
#84
0!
#85
1!
#86
0!
#87
1!
#88
0!
#89
b10 "
b1100 %
1#
1!
#90
0!
#91
1!
#92
0!
#93
1!
#94
0!
#95
1!
#96
0!
#97
1!
#98
0!
#99
0#
1!
