FPGA/verilog_working_directory/src/verilog_basics/02_basics_01.v
module stimulus;
	
	reg x,y,a,b,m,p;

	initial
	begin
		$dumpfile("test.vcd");
		$dumpvars(0,x,y,a,b,m,p);
	end

	initial
	begin
		p = 1'b0;
		m = 1'b0;
	end

	initial 
	begin
		#5 a = 1'b1;
		#25 b = 1'b0;
	end

	initial
	begin
		#10 x = 1'b0;
		#25 y = 1'b1;
	end

	// initial 
	// begin
	// 	p = 1'b0;
	// 	#5 p = 1'b1;
	// 	#5 p = 1'b0;
	// 	#5 p = 1'b1;
	// 	#5 p = 1'b0;
	// 	#5 p = 1'b1;
	// 	#5 p = 1'b0;
	// 	#5 p = 1'b1;
	// 	#5 p = 1'b0;
	// 	#5 p = 1'b1;
	// 	#5 p = 1'b0;
	// end

	always
		#2 p = ~p;

	initial
		#50 $finish;

	// always
	// 	#5 $display("the current time is %t",$time);

	initial 
		#30 $stop;

endmodule

FPGA/verilog_working_directory/src/verilog_basics/test.vcd
$date
	Thu Feb 18 23:34:59 2016
$end
$version
	Icarus Verilog
$end
$timescale
	1s
$end
$scope module stimulus $end
$var reg 1 ! x $end
$upscope $end
$scope module stimulus $end
$var reg 1 " y $end
$upscope $end
$scope module stimulus $end
$var reg 1 # a $end
$upscope $end
$scope module stimulus $end
$var reg 1 $ b $end
$upscope $end
$scope module stimulus $end
$var reg 1 % m $end
$upscope $end
$scope module stimulus $end
$var reg 1 & p $end
$upscope $end
$enddefinitions $end
#0
$dumpvars
0&
0%
x$
x#
x"
x!
$end
#2
1&
#4
0&
#5
1#
#6
1&
#8
0&
#10
1&
0!
#12
0&
#14
1&
#16
0&
#18
1&
#20
0&
#22
1&
#24
0&
#26
1&
#28
0&
